batch_metric/__init__.py
batch_metric/classification.py
batch_metric/collector.py
batch_metric/regression.py
batch_metric/utils.py
batch_metric-0.3.dist-info/METADATA
batch_metric-0.3.dist-info/WHEEL
batch_metric-0.3.dist-info/top_level.txt
batch_metric-0.3.dist-info/RECORD
