Metadata-Version: 2.1
Name: batch-metric
Version: 0.3
Summary: Tool for calculating metric by batch updates.
Home-page: https://github.com/darkhan-ai/batch-metric
License: MIT
Requires-Dist: scikit-learn
